radage/__init__.py
radage/helper.py
radage/plotting.py
radage/radage.py
radage-0.1.0.dist-info/licenses/LICENSE.txt
radage-0.1.0.dist-info/METADATA
radage-0.1.0.dist-info/WHEEL
radage-0.1.0.dist-info/top_level.txt
radage-0.1.0.dist-info/RECORD
